lzhsys/__init__.py
lzhsys/process.py
lzhsys-1.0.0.dist-info/METADATA
lzhsys-1.0.0.dist-info/WHEEL
lzhsys-1.0.0.dist-info/top_level.txt
lzhsys-1.0.0.dist-info/RECORD
