Metadata-Version: 2.1
Name: lzhsys
Version: 1.0.0
Author-email: zhlei <leizuoho@mail.ustc.edu.cn>
Requires-Python: >=3.0
Requires-Dist: lzhlog
